README.md
setup.cfg
setup.py
monstercatFM/__init__.py
monstercatFM/monstercat.py
monstercatFM.egg-info/PKG-INFO
monstercatFM.egg-info/SOURCES.txt
monstercatFM.egg-info/dependency_links.txt
monstercatFM.egg-info/requires.txt
monstercatFM.egg-info/top_level.txt