Metadata-Version: 1.1
Name: monstercatFM
Version: 1.1.1
Summary: Unofficial shitty API wrapper to get information about the monstercat live stream
Home-page: https://github.com/Zenrac/monstercatFM
Author: Zenrac
Author-email: zenrac@outlook.fr
License: UNKNOWN
Download-URL: https://github.com/Zenrac/monstercatFM/archive/v1.1.1.tar.gz
Keywords: MonstercatFM,Monstercat live stream,MCTL
Platform: UNKNOWN
